pds/peppi/VERSION.txt
pds/peppi/__init__.py
pds/peppi/client.py
pds/peppi/products.py
pds/peppi/query_builder.py
pds/peppi/result_set.py
pds/peppi/orex/__init__.py
pds/peppi/orex/products.py
pds/peppi/orex/query_builder.py
pds_notpeppi-6.87.0.dist-info/licenses/LICENSE.md
pds_notpeppi-6.87.0.dist-info/licenses/NOTICE.txt
pds_notpeppi-6.87.0.dist-info/METADATA
pds_notpeppi-6.87.0.dist-info/WHEEL
pds_notpeppi-6.87.0.dist-info/top_level.txt
pds_notpeppi-6.87.0.dist-info/zip-safe
pds_notpeppi-6.87.0.dist-info/RECORD
